README.md
setup.py
pygrouplib/__init__.py
pygrouplib/numericgrouper.py
pygrouplib/textgrouper.py
pygrouplib.egg-info/PKG-INFO
pygrouplib.egg-info/SOURCES.txt
pygrouplib.egg-info/dependency_links.txt
pygrouplib.egg-info/top_level.txt