Metadata-Version: 2.1
Name: pygrouplib
Version: 1.0.4
Summary: Library for clustering entities based on numeric or text value.
Home-page: https://github.com/popovicn/pygrouplib
Author: Nenad Popovic
Author-email: popovic0706@gmail.com
License: UNKNOWN
Keywords: group fuzzy approximate levenshtein text numeric
Platform: UNKNOWN
Classifier: Programming Language :: Python :: 3
Classifier: License :: OSI Approved :: GNU General Public License v3 (GPLv3)
Classifier: Operating System :: OS Independent
Requires-Python: >=2.7
